kolibri_dynamic_collections_plugin/__init__.py
kolibri_dynamic_collections_plugin/api.py
kolibri_dynamic_collections_plugin/api_urls.py
kolibri_dynamic_collections_plugin/kolibri_plugin.py
kolibri_dynamic_collections_plugin/urls.py
kolibri_dynamic_collections_plugin/views.py
kolibri_dynamic_collections_plugin/build/kolibri_dynamic_collections_plugin.app_stats.json
kolibri_dynamic_collections_plugin/build/kolibri_dynamic_collections_plugin.side_nav_stats.json
kolibri_dynamic_collections_plugin/static/kolibri_dynamic_collections_plugin.app/kolibri_dynamic_collections_plugin.app-1.0.0.js
kolibri_dynamic_collections_plugin/static/kolibri_dynamic_collections_plugin.app/kolibri_dynamic_collections_plugin.app-1.0.0.js.map
kolibri_dynamic_collections_plugin/static/kolibri_dynamic_collections_plugin.app/kolibri_dynamic_collections_plugin.app-1.0.1.js
kolibri_dynamic_collections_plugin/static/kolibri_dynamic_collections_plugin.app/kolibri_dynamic_collections_plugin.app-1.0.1.js.map
kolibri_dynamic_collections_plugin/static/kolibri_dynamic_collections_plugin.app/kolibri_dynamic_collections_plugin.app-1.1.0.js
kolibri_dynamic_collections_plugin/static/kolibri_dynamic_collections_plugin.app/kolibri_dynamic_collections_plugin.app-1.1.0.js.map
kolibri_dynamic_collections_plugin/static/kolibri_dynamic_collections_plugin.app/kolibri_dynamic_collections_plugin.app-1.2.0.js
kolibri_dynamic_collections_plugin/static/kolibri_dynamic_collections_plugin.app/kolibri_dynamic_collections_plugin.app-1.2.0.js.map
kolibri_dynamic_collections_plugin/static/kolibri_dynamic_collections_plugin.app/kolibri_dynamic_collections_plugin.app-1.3.0.js
kolibri_dynamic_collections_plugin/static/kolibri_dynamic_collections_plugin.app/kolibri_dynamic_collections_plugin.app-1.3.0.js.map
kolibri_dynamic_collections_plugin/static/kolibri_dynamic_collections_plugin.app/kolibri_dynamic_collections_plugin.app-1.4.0.js
kolibri_dynamic_collections_plugin-1.5.1.dist-info/LICENSE
kolibri_dynamic_collections_plugin-1.5.1.dist-info/METADATA
kolibri_dynamic_collections_plugin-1.5.1.dist-info/WHEEL
kolibri_dynamic_collections_plugin-1.5.1.dist-info/entry_points.txt
kolibri_dynamic_collections_plugin-1.5.1.dist-info/top_level.txt
kolibri_dynamic_collections_plugin-1.5.1.dist-info/RECORD
