Metadata-Version: 2.1
Name: kolibri-dynamic-collections-plugin
Version: 1.5.1
Summary: Kolibri plugin to add a Zim file viewer
Home-page: https://github.com/endlessm/kolibri-dynamic-collections-plugin
Author: Endless OS Foundation
Author-email: dylan@endlessos.org
License: MIT
Keywords: kolibri
Classifier: Development Status :: 2 - Pre-Alpha
Classifier: Intended Audience :: Developers
Classifier: License :: OSI Approved :: MIT License
Classifier: Natural Language :: English
Classifier: Programming Language :: Python :: 3
Classifier: Programming Language :: Python :: 3.6
Classifier: Programming Language :: Python :: 3.7
Classifier: Programming Language :: Python :: 3.8
Classifier: Programming Language :: Python :: 3.9
Classifier: Programming Language :: Python :: 3.10
Classifier: Programming Language :: Python :: 3.11
Classifier: Programming Language :: Python :: Implementation :: PyPy
License-File: LICENSE
